pyodps_catalog/__init__.py
pyodps_catalog/client.py
pyodps_catalog/models.py
pyodps_catalog-1.0.0.dist-info/METADATA
pyodps_catalog-1.0.0.dist-info/WHEEL
pyodps_catalog-1.0.0.dist-info/top_level.txt
pyodps_catalog-1.0.0.dist-info/RECORD
