Metadata-Version: 2.4
Name: pyodps_catalog
Version: 1.0.0
Summary: Alibaba Cloud MaxCompute openapi SDK Library for Python
Home-page: https://github.com/aliyun/darabonba-openapi
Author: Alibaba Cloud SDK
Author-email: sdk-team@alibabacloud.com
License: Apache License 2.0
Keywords: pyodps,catalog
Platform: any
Classifier: Development Status :: 4 - Beta
Classifier: Intended Audience :: Developers
Classifier: License :: OSI Approved :: Apache Software License
Classifier: Programming Language :: Python
Classifier: Programming Language :: Python :: 3
Classifier: Programming Language :: Python :: 3.6
Classifier: Programming Language :: Python :: 3.7
Classifier: Programming Language :: Python :: 3.8
Classifier: Programming Language :: Python :: 3.9
Classifier: Topic :: Software Development
Requires-Python: >=3.6
Requires-Dist: maxcompute_tea_openapi<2.0.0,>=1.1.0
Requires-Dist: alibabacloud_tea_util<1.0.0,>=0.3.13
Requires-Dist: maxcompute_tea_util<1.0.0,>=0.0.1
Dynamic: author
Dynamic: author-email
Dynamic: classifier
Dynamic: description-content-type
Dynamic: home-page
Dynamic: keywords
Dynamic: license
Dynamic: platform
Dynamic: requires-dist
Dynamic: requires-python
Dynamic: summary
